kikit/__init__.py
kikit/_version.py
kikit/annotations.py
kikit/common.py
kikit/defs.py
kikit/doc.py
kikit/drc.py
kikit/drc_ui.py
kikit/eeschema.py
kikit/eeschema_v6.py
kikit/export.py
kikit/export_ui.py
kikit/fab_ui.py
kikit/info.py
kikit/intervals.py
kikit/kicadUtil.py
kikit/modify.py
kikit/modify_ui.py
kikit/panelize.py
kikit/panelize_ui.py
kikit/panelize_ui_impl.py
kikit/panelize_ui_sections.py
kikit/pcbnew_utils.py
kikit/plugin.py
kikit/present.py
kikit/present_ui.py
kikit/project.py
kikit/sexpr.py
kikit/stencil.py
kikit/stencil_ui.py
kikit/substrate.py
kikit/text.py
kikit/typing.py
kikit/ui.py
kikit/units.py
kikit/actionPlugins/__init__.py
kikit/actionPlugins/common.py
kikit/actionPlugins/hideReferences.py
kikit/actionPlugins/panelize.py
kikit/fab/__init__.py
kikit/fab/common.py
kikit/fab/jlcpcb.py
kikit/fab/neodenyy1.py
kikit/fab/openpnp.py
kikit/fab/oshpark.py
kikit/fab/pcbway.py
kikit/panel_features/__init__.py
kikit/panel_features/baseFeature.py
kikit/panel_features/copperFill.py
kikit/resources/kikit.kicad_sym
kikit/resources/graphics/kikitIcon.svg
kikit/resources/graphics/kikitIcon_48x48.png
kikit/resources/graphics/kikitIcon_64x64.png
kikit/resources/graphics/panelizeIcon.svg
kikit/resources/graphics/panelizeIcon_24x24.png
kikit/resources/graphics/pcbBg.png
kikit/resources/graphics/removeRefIcon.svg
kikit/resources/graphics/removeRefIcon_24x24.png
kikit/resources/kikit.pretty/Board.kicad_mod
kikit/resources/kikit.pretty/Error.kicad_mod
kikit/resources/kikit.pretty/Fiducial.kicad_mod
kikit/resources/kikit.pretty/NPTH.kicad_mod
kikit/resources/kikit.pretty/Tab.kicad_mod
kikit/resources/panelizePresets/default.json
kikit/resources/panelizePresets/jlcTooling.json
kikit/resources/panelizePresets/jlcVcuts.json
kikit/resources/present/templates/default/.gitignore
kikit/resources/present/templates/default/index.html
kikit/resources/present/templates/default/template.json
kikit/resources/present/templates/default/css/styles.css
KiKit-1.7.2.dist-info/LICENCE
KiKit-1.7.2.dist-info/METADATA
KiKit-1.7.2.dist-info/WHEEL
KiKit-1.7.2.dist-info/entry_points.txt
KiKit-1.7.2.dist-info/top_level.txt
KiKit-1.7.2.dist-info/RECORD
