Metadata-Version: 2.1
Name: KiKit
Version: 1.7.2
Summary: Automation for KiCAD boards
Home-page: https://github.com/yaqwsx/KiKit
Author: Jan Mrázek
Author-email: email@honzamrazek.cz
License: UNKNOWN
Platform: UNKNOWN
Classifier: Programming Language :: Python :: 3
Classifier: License :: OSI Approved :: MIT License
Classifier: Operating System :: OS Independent
Requires-Python: >=3.7
License-File: LICENCE
Requires-Dist: click (>=7.1)
Requires-Dist: commentjson (>=0.9)
Requires-Dist: markdown2 (>=2.4)
Requires-Dist: numpy
Requires-Dist: pcbnewTransition (<=0.6,>=0.5.2)
Requires-Dist: pybars3 (>=0.9)
Requires-Dist: shapely (>=2.0.3)
Requires-Dist: solidpython (>=1.1.2)
Provides-Extra: dev
Requires-Dist: pytest ; extra == 'dev'
